zeropush
