Metadata-Version: 1.0
Name: django-zeropush
Version: 0.2.2
Summary: ZeroPush iOS push notifications support for django
Home-page: https://github.com/hakanw/django-zeropush
Author: Håkan Waara
Author-email: hwaara@gmail.com
License: BSD licence, see LICENCE.txt
Platform: UNKNOWN
